{
  "id": "mem_1774666715286_90877e49",
  "type": "episodic",
  "content": "Task (code): I need you to continue on the HellowWOrld OVerEngineered project we need to over engin a helloworld script it has to go thru multi steps over multi scripts \n\nFalow the Writing and commenting guide\nResult: ****Design the architecture** - Map out the pipeline: Config → Validator → Encoder → Processor → Decoder → Formatter → Output Handler → Logger. Each step is its own script/module.**\n## Step 1 Summary\n\n**Designed the architecture and created 3 of 8+ planned files:**\n\n1. **`hello-world/ARCHITECTURE.md`** — Full pipeline map documenting the 8-stage flow: Config → Validator → Encoder → Processor → Decoder → Formatter → Output Handler → Logger, with descriptions of each module's role.\n\n2. **`hello-wo",
  "topics": [
    "code",
    "full pipeline map documenting",
    "hellowworld overengineered project",
    "helloworld script",
    "multi scripts",
    "commenting guide",
    "output handler",
    "planned files",
    "8stage flow",
    "task",
    "task code",
    "code need"
  ],
  "summary": "Task (code): I need you to continue on the HellowWOrld OVerEngineered project we need to over engin a helloworld script it has to go thru multi steps over multi scripts \n\nFalow the Writing and comment",
  "importance": 0.5,
  "createdAt": 1774666715290,
  "createdAtISO": "2026-03-28T02:58:35.290Z",
  "chainId": "chain_1774666303921_57vxk8",
  "archive": null,
  "sourcePath": null,
  "accessCount": 0
}