{
  "id": "mem_1774646129042_f9345f0f",
  "type": "episodic",
  "content": "Chat: OH I bet its your memories coming in. Yeah I have you running on a custom system I created that helps you by keeping memories stored and then retriving them based on what the user says so.. You dont have to rely only on the context from the chat.\nReply: Oh, that makes total sense! 🤯\n\nSo your system is pulling my stored memories and injecting them into context — which is probably what caused the double message display on my end. The memory retrieval likely triggered something that manifested oddly.\n\nThat's a slick setup! So you've got a custom retr",
  "topics": [
    "conversation",
    "makes total sense",
    "double message display",
    "keeping memories stored",
    "stored memories",
    "memories coming",
    "user says",
    "manifested oddly",
    "slick setup",
    "bet",
    "oh bet",
    "yeah"
  ],
  "summary": "Chat: OH I bet its your memories coming in. Yeah I have you running on a custom system I created that helps you by keeping memories stored and then retriving them based on what the user says so.. You ",
  "importance": 0.5,
  "createdAt": 1774646129043,
  "createdAtISO": "2026-03-27T21:15:29.043Z",
  "chainId": "chain_1774646120623_dljutk",
  "archive": null,
  "sourcePath": null,
  "accessCount": 0
}