{
  "id": "mem_1774646387118_db23725d",
  "type": "semantic",
  "content": "**DO:**\r\n- Write in accessible language — students should understand this, not just professors\r\n- Include concrete examples for every abstract concept\r\n- Vary question difficulty — some easy wins, some deep thinking\r\n- Use analogies liberally — they are the best learning tool\r\n- Keep flashcard fronts short and unambiguous\r\n- Structure timelines chronologically, always\r\n\n**DON'T:**\r\n- Copy textbook language verbatim — rephrase for clarity\r\n- Make all practice questions trivial — include questions that require synthesis\r\n- Skip the concept relationships — understanding connections is the point\r\n- Generate flashcards without tagging difficulty — spaced repetition needs this\r\n- Present outlines without offering restructuring options\r\n- List timeline events without causal connections — isolated facts don't teach",
  "topics": [
    "MA Memory Architect",
    "study_guide.md",
    "MA-blueprints modules"
  ],
  "summary": "**DO:**\r\n- Write in accessible language — students should understand this, not just professors\r\n- Include concrete examples for every abstract concept\r\n- Vary question difficulty — some easy wins, som",
  "importance": 0.6,
  "createdAt": 1774646387119,
  "createdAtISO": "2026-03-27T21:19:47.119Z",
  "chainId": null,
  "archive": "MA Memory Architect",
  "sourcePath": "MA-blueprints\\modules\\study_guide.md",
  "accessCount": 0
}