{
  "id": "mem_1774646384782_62462119",
  "type": "semantic",
  "content": "// MA UI — Chat, session management, typing indicators, progress widget, send/receive.\r\n\n// ── Session state ─────────────────────────────────────────────────────────\r\nlet activeSessionId = null; // null = new session (not yet saved)\r\nlet allSessions = [];       // cached session list from server\r\n\n// ── Long-request timeout popup ────────────────────────────────────────────\r\nconst LONG_REQUEST_THRESHOLD = 30000; // 30s before showing popup\r\nconst AUTOPILOT_KEY = 'ma-autopilot-v1';\r\nlet _lrTimer = null;\r\nlet _lrStartTime = 0;\r\nlet _lrAbortController = null;\r\nlet _lrDismissed = false;\r\n\nfunction isAutoPilot() { return localStorage.getItem(AUTOPILOT_KEY) === '1'; }\r\nfunction setAutoPilot(on) { localStorage.setItem(AUTOPILOT_KEY, on ? '1' : '0'); }\r\n\nfunction _startLongRequestTimer() {\r\n  _lrStartTime = Date.now();\r\n  _lrDismissed = false;\r\n  _clearLongRequestTimer();\r\n  if (isAutoPilot()) return; // no popups in auto pilot\r\n  _lrTimer = setTimeout(_showLongRequestPopup, LONG_REQUEST_THRESHOLD);\r\n}\r\n\nfunction _resetLongRequestTimer() {\r\n  // Reset on any progress event (SSE activity/step)\r\n  if (_lrDismissed || isAutoPilot()) return;\r\n  _clearLongRequestTimer();\r\n  _lrTimer = setTimeout(_showLongRequestPopup, LONG_REQUEST_THRESHOLD);\r\n}\r\n\nfunction _clearLongRequestTimer() {\r\n  if (_lrTimer) { clearTimeout(_lrTimer); _lrTimer = null; }\r\n}",
  "topics": [
    "MA Memory Architect",
    "ma-ui-chat.js",
    "FrontEnd js"
  ],
  "summary": "// MA UI — Chat, session management, typing indicators, progress widget, send/receive.\r\n\n// ── Session state ─────────────────────────────────────────────────────────\r\nlet activeSessionId = null; // n",
  "importance": 0.6,
  "createdAt": 1774646384783,
  "createdAtISO": "2026-03-27T21:19:44.783Z",
  "chainId": null,
  "archive": "MA Memory Architect",
  "sourcePath": "FrontEnd\\js\\ma-ui-chat.js",
  "accessCount": 0
}