{
  "id": "mem_1774646385074_c5beaec4",
  "type": "semantic",
  "content": "function renderTreeNodes(nodes, depth) {\r\n  return nodes.map(function(node) {\r\n    if (node.type === 'directory') {\r\n      const children = node.children ? renderTreeNodes(node.children, depth + 1) : '';\r\n      return '<div class=\"tree-node\" style=\"margin-left:' + (depth * 12) + 'px\">' +\r\n        '<div class=\"tree-row\" onclick=\"toggleTreeDir(this)\">' +\r\n          '<span class=\"tree-toggle\">▶</span>' +\r\n          '<span>📁 ' + escHtml(node.name) + '</span>' +\r\n        '</div>' +\r\n        '<div class=\"tree-children\" style=\"display:none\">' + children + '</div>' +\r\n      '</div>';\r\n    }\r\n    const ext = (node.name.match(/\\.([^.]+)$/) || [])[1] || '';\r\n    const icon = fileIcon(ext);\r\n    return '<div class=\"tree-node\" style=\"margin-left:' + (depth * 12) + 'px\">' +\r\n      '<button class=\"explorer-item\" onclick=\"openFileInEditor(\\'' + escAttr(node.path) + '\\')\">' +\r\n        '<span>' + icon + '</span>' +\r\n        '<span>' + escHtml(node.name) + '</span>' +\r\n        '<span class=\"meta\">' + escHtml(ext.toUpperCase()) + '</span>' +\r\n      '</button>' +\r\n    '</div>';\r\n  }).join('');\r\n}\r\n\nfunction escAttr(s) { return s.replace(/\\\\/g, '\\\\\\\\').replace(/'/g, \"\\\\'\"); }\r\n\nfunction toggleTreeDir(rowEl) {\r\n  const children = rowEl.nextElementSibling;\r\n  const toggle = rowEl.querySelector('.tree-toggle');\r\n  if (!children) return;\r\n  const open = children.style.display !== 'none';\r\n  children.style.display = open ? 'none' : '';\r\n  toggle.textContent = open ? '▶' : '▼';\r\n}",
  "topics": [
    "MA Memory Architect",
    "ma-ui-editor.js",
    "FrontEnd js"
  ],
  "summary": "function renderTreeNodes(nodes, depth) {\r\n  return nodes.map(function(node) {\r\n    if (node.type === 'directory') {\r\n      const children = node.children ? renderTreeNodes(node.children, depth + 1) : ",
  "importance": 0.6,
  "createdAt": 1774646385074,
  "createdAtISO": "2026-03-27T21:19:45.074Z",
  "chainId": null,
  "archive": "MA Memory Architect",
  "sourcePath": "FrontEnd\\js\\ma-ui-editor.js",
  "accessCount": 0
}