{
  "id": "mem_1774646382701_fd8edea1",
  "type": "semantic",
  "content": "Chat: Hey Ma you there\nReply: Hey! Yeah, I'm here. 👋\n\nI'm MA, your Memory Architect — I can help with memory storage and retrieval, research, coding, and general tasks. \n\nWhat can I do for you today?",
  "topics": [
    "MA Memory Architect",
    "semantic.txt",
    "BackEnd MA-entity entity_ma memories episodic mem_1774646025346_a5bfb5b7"
  ],
  "summary": "Chat: Hey Ma you there\nReply: Hey! Yeah, I'm here. 👋\n\nI'm MA, your Memory Architect — I can help with memory storage and retrieval, research, coding, and general tasks. \n\nWhat can I do for you today?",
  "importance": 0.6,
  "createdAt": 1774646382702,
  "createdAtISO": "2026-03-27T21:19:42.702Z",
  "chainId": null,
  "archive": "MA Memory Architect",
  "sourcePath": "BackEnd\\MA-entity\\entity_ma\\memories\\episodic\\mem_1774646025346_a5bfb5b7\\semantic.txt",
  "accessCount": 0
}